AUTHORS
LICENSE
MANIFEST.in
README.rst
setup.py
django_staticfiles.egg-info/PKG-INFO
django_staticfiles.egg-info/SOURCES.txt
django_staticfiles.egg-info/dependency_links.txt
django_staticfiles.egg-info/not-zip-safe
django_staticfiles.egg-info/top_level.txt
docs/Makefile
docs/changelog.rst
docs/commands.rst
docs/conf.py
docs/helpers.rst
docs/index.rst
docs/make.bat
docs/settings.rst
staticfiles/__init__.py
staticfiles/context_processors.py
staticfiles/finders.py
staticfiles/handlers.py
staticfiles/models.py
staticfiles/settings.py
staticfiles/storage.py
staticfiles/urls.py
staticfiles/utils.py
staticfiles/views.py
staticfiles/management/__init__.py
staticfiles/management/commands/__init__.py
staticfiles/management/commands/collectstatic.py
staticfiles/management/commands/findstatic.py
staticfiles/management/commands/runserver.py
staticfiles/templatetags/__init__.py
staticfiles/templatetags/static.py
staticfiles/templatetags/staticfiles.py