Metadata-Version: 1.0
Name: django-staticfiles
Version: 1.1
Summary: A Django app that provides helpers for serving static files.
Home-page: http://django-staticfiles.readthedocs.org/
Author: Jannis Leidel
Author-email: jannis@leidel.info
License: BSD
Platform: UNKNOWN
Classifier: Development Status :: 3 - Alpha
Classifier: Environment :: Web Environment
Classifier: Intended Audience :: Developers
Classifier: License :: OSI Approved :: BSD License
Classifier: Operating System :: OS Independent
Classifier: Programming Language :: Python
Classifier: Framework :: Django
